cipher_parse/__init__.py
cipher_parse/_version.py
cipher_parse/cipher_input.py
cipher_parse/cipher_output.py
cipher_parse/derived_outputs.py
cipher_parse/discrete_voronoi.py
cipher_parse/errors.py
cipher_parse/example_data/__init__.py
cipher_parse/example_data/dream3d/2D/__init__.py
cipher_parse/example_data/dream3d/2D/synthetic_d3d.dream3d
cipher_parse/example_data/dream3d/2D/synthetic_d3d.json
cipher_parse/example_data/dream3d/2D/synthetic_d3d.xdmf
cipher_parse/example_data/dream3d/3D/__init__.py
cipher_parse/example_data/dream3d/3D/synthetic_d3d.dream3d
cipher_parse/example_data/dream3d/3D/synthetic_d3d.json
cipher_parse/example_data/dream3d/3D/synthetic_d3d.xdmf
cipher_parse/geometry.py
cipher_parse/interface.py
cipher_parse/material.py
cipher_parse/quats.py
cipher_parse/utilities.py
cipher_parse/voxel_map.py
cipher_parse-0.5.0.dist-info/LICENSE
cipher_parse-0.5.0.dist-info/METADATA
cipher_parse-0.5.0.dist-info/WHEEL
cipher_parse-0.5.0.dist-info/RECORD
