Metadata-Version: 2.1
Name: cipher-parse
Version: 0.5.0
Summary: Pre- and post-processing for the phase-field code CIPHER.
License: MIT
Author: aplowman
Author-email: adam.plowman@manchester.ac.uk
Requires-Python: >=3.8,<3.11
Classifier: License :: OSI Approved :: MIT License
Classifier: Programming Language :: Python :: 3
Classifier: Programming Language :: Python :: 3.8
Classifier: Programming Language :: Python :: 3.9
Classifier: Programming Language :: Python :: 3.10
Provides-Extra: hickle
Provides-Extra: matflow
Provides-Extra: notebook
Requires-Dist: damask (>=3.0.0-alpha.6,<4.0.0)
Requires-Dist: h5py (==2.10.0)
Requires-Dist: hickle (==4.0.4) ; extra == "hickle" or extra == "matflow"
Requires-Dist: ipywidgets (<8.0.0)
Requires-Dist: itkwidgets (>=0.25.2)
Requires-Dist: matflow (>=0.2.26,<0.3.0) ; extra == "matflow"
Requires-Dist: nbformat (>=5.4.0,<6.0.0)
Requires-Dist: notebook (>=6.5.1,<7.0.0) ; extra == "notebook"
Requires-Dist: numpy (==1.21)
Requires-Dist: pandas (>=1.5.1,<2.0.0)
Requires-Dist: parse (>=1.19.0,<2.0.0)
Requires-Dist: plotly (>=5.9.0,<6.0.0)
Requires-Dist: pyvista (>=0.39.0,<0.40.0)
Requires-Dist: ruamel.yaml (>=0.17.21,<0.18.0)
Requires-Dist: sqlalchemy (<2.0.0) ; extra == "matflow"
Requires-Dist: trame (>=2.4.2,<3.0.0)
Requires-Dist: vecmaths (>=0.1.6,<0.2.0)
